setup.py
funnny/__init__.py
funnny/joke.py
funnny.egg-info/PKG-INFO
funnny.egg-info/SOURCES.txt
funnny.egg-info/dependency_links.txt
funnny.egg-info/not-zip-safe
funnny.egg-info/top_level.txt