Metadata-Version: 1.0
Name: funnny
Version: 0.2
Summary: The funniest joke in the world
Home-page: http://github.com/jeremyzhang2008/funniestjoke
Author: Jeremy Zhang
Author-email: jeremy.zhangzq@gmail.com
License: MIT
Platform: UNKNOWN
